uw_myplan/VERSION
uw_myplan/__init__.py
uw_myplan/dao.py
uw_myplan/models.py
uw_myplan/test.py
uw_myplan/utils.py
uw_myplan/resources/myplan/file/plan/v1/2013_spring_4_9136CCB8F66711D5BE060004AC494FFE
uw_myplan/resources/myplan_auth/file/oauth2/token.POST
uw_myplan/tests/__init__.py
uw_myplan/tests/test_dao.py
uw_myplan/tests/test_myplan.py
uw_restclients_myplan-1.3.1.dist-info/licenses/LICENSE
uw_restclients_myplan-1.3.1.dist-info/METADATA
uw_restclients_myplan-1.3.1.dist-info/WHEEL
uw_restclients_myplan-1.3.1.dist-info/top_level.txt
uw_restclients_myplan-1.3.1.dist-info/RECORD
